paddlelite/__init__.py
paddlelite/lite.so
paddlelite/libs/libiomp5.so
paddlelite/libs/libmklml_intel.so
paddleslim_opt_tools-2.11.2.data/scripts/paddle_lite_opt
paddleslim_opt_tools-2.11.2.dist-info/METADATA
paddleslim_opt_tools-2.11.2.dist-info/WHEEL
paddleslim_opt_tools-2.11.2.dist-info/top_level.txt
paddleslim_opt_tools-2.11.2.dist-info/RECORD
