Metadata-Version: 2.1
Name: paddleslim-opt-tools
Version: 2.11.2
Summary: Paddle-Lite Library
